{"person_Id": "0138", "source_text": "二十年代由日本北海道传入的大型藻类——海带，味美可口，营养丰富，又能防治甲状腺肿病。但海带是一种喜欢低温的冷温带孢子植物。曾呈奎教授便组织了海带南移试验，一举成功，不久后便形成了大规模养殖。从1952年冬季开始，曾呈奎教授又带领他的助手和大学生，在青岛、烟台、大连等地近海内，用人工培植的方法，建起了一大片一大片的海带生产田。他们还不断总结栽培技术，进一步研究其生长规律和环境习性，并大胆采用农作物密植方法，大大提高了海带的单位面积产量。五十年代初，中国海带产量仅有60吨，每年要进口十数吨，才能满足市场需求。而到1985年，中国年产海带干品已达250万吨，占海带植物世界年产量的80%,成为世界头号海带养殖生产大国，每年都有大量产品销往世界各国。如今，我国沿海布满了大小不一、成方成块的海带种植田，年年都获得大丰收。这既支援了国家建设，增加了外汇收入，又大大增加了渔民的收入，改善了人民的生活。这不能不使人想到当年科学家们对海藻研究试验的艰难岁月，更不能不感谢至今已有92岁高龄的曾呈奎这位老科学家为此所倾注的一片心血！", "ei": "", "pc": "", "tm": "", "loc": "", "sm": ""}