{"person_Id": "0138", "source_text": "1940年曾呈奎得到了美国密西根大学的奖学金资助赴美国攻读博士学位。1942年5月完成了博士论文答辩并获得博士学位，由于二次大战爆发的原因，不得不滞留美国。战争年代，曾呈奎利用停留美国的机会，在“斯克里普斯海洋研究所”进一步扩展曾呈奎在海洋学和海藻学方面的知识，在此期间，曾呈奎最重要的贡献可能就是对潮下带海藻首次进行的现场研究，曾呈奎使用了头盔式潜水装备，观察和记录了大石花等海藻的生长率，该种海藻是加利福尼亚沿海出产的重要琼胶原料，由于琼胶、褐藻胶一向都是由日本供应的战略物资，到了战争年代得不到供应，因而寻求新的原料来源就成为非常重要的任务。为了发展这些海藻供应方面的科技问题，曾呈奎和工业界人士密切合作开展研究，到了二次大战结束时，曾呈奎已成为海藻工业和食品利用方面最具有权威性的领军人物。由曾呈奎敲定的(藻胶)这一学术名词包含了一大类海洋化学产品，曾呈奎还参与了美国藻类学会的组建，与此同时曾呈奎和马克斯威尔·道蒂教授建立了长远的友谊，他们对发展海洋农业的潜力具有同样的信念。", "ei": "", "pc": "", "tm": "", "loc": "", "sm": ""}