{"person_Id": "0142", "source_text": "5岁的时候，李四光开始跟一位姓陈的老先生启蒙，6岁转到父亲的私塾里，随父亲念书。私塾里，同学们都在校住宿。有一天夜里，天气特别的寒冷，大家把所有的衣服都压在被子上面。半夜里，一个小偷溜进学生宿舍，把一个同学盖在被子上的衣服给偷走了。那小偷正在溜出去时，碰倒了桌子，响声惊醒了一位同学，他见陌生人进来，便大声喊道：\"有小偷，大家快起来抓小偷！\"同学们全都惊醒了，冲出院子去捉贼。不一会儿，小偷就被同学们抓了回来。只见那小偷一身褴褛，脸色腊黄。同学们你一拳、我一脚地把小偷打得鼻青脸肿。\"大家不要再打他了：\"站在一旁一直没有动手的李四光实在看不下去了，就向同学们喊道。同学们住了手，一齐望着他们最尊敬的老大哥。李四光走上前对那位小偷说：\"你以后再不能偷东西了。做了坏事，别人就要打你。你以后做个好人吧！\"小偷点了一下头，眼泪扑簌簌掉了下来。有的同学围上来埋怨李四光：\"他偷了别人的衣服，也想偷你的，你为什么要帮助他?\"李四光说道：\"你们看他穿得那么单薄，又被打了一顿，实在可怜，放了他吧。我想他今后会改的。\"小偷被放走了，临走时，他向李四光深深地鞠了一躬。", "ei": "", "pc": "", "tm": "", "loc": "", "sm": ""}