{"person_Id": "0142", "source_text": "在长期的国外留学生活中，李四光亲身感受到中国人受尽歧视的耻辱，从而产生了强烈的民族自尊心。他曾说：“我们不能不承认人家的文化程度比我们高，艺术比我们精。人家的地方已经开辟到十分田地，我们的一块沃土，还在那里荒着。请他们来做好了，再拱手奉还给我们，世界上恐怕没有那么一回事。所以，我们一线的生机，还是在我们的民族，大家打起精神，举起锄头向前挖去。”所以，李四光上课的时候，除了科学上的一些专有名词以外，他始终坚持用中文讲解。有一次，上课的时候，一个学生叫他“Mr.李”，叫了几声，他就问那个学生叫谁？那个学生说：“叫你。”李四光说：“你可以称我老李、小李或阿猫、阿狗什么的，但是我不准你叫我‘Mr.李’。”有一次，李四光带了七八个学生到宜昌做野外考察，在街上看见一个美国人坐人力车不给车钱，还要拿起手杖打拉车人。李四光看到后，气愤极了，就跑到美国人面前一定要他付车钱，并且不准打人。那个美国人开始愣了一下，后来一看是一个穿破西服的中国人，竟蛮不讲理地冷笑一下，准备一走了之。李四光和七八个学生操起地质锤把他拦住了。那个美国人一看事情不妙，只得乖乖地给了车钱，灰溜溜地走了。路上的行人都为此感到扬眉吐气。", "ei": "", "pc": "", "tm": "", "loc": "", "sm": ""}