{"person_Id": "0121", "source_text": "50年代，周培源利用一个比较简单的轴对称涡旋模型作为湍流元的物理图像来说明均匀各向同性的湍流运动，并根据对均匀各向同性的湍流运动的研究，分别求得在湍流衰变后期和初期的二元速度的关联函数、三元速度关联函数。之后，他又进一步用\"准相似性\"概念将衰变初期和后期的相似条件统一为一个确定解的物理条件，并为实验所证实。从而在国际上第一次由实验确定了从衰变初期到后期的湍流能量衰变规律和泰勒湍流微尺度扩散规律的理论结果。他首先提出了以研究湍流的基本涡旋结构作为出发点，以某种典型旋涡作为湍流元，采用先求解后求平均的新方法，从而避免了传统湍流理论中纳维-斯托克斯方程出现不封闭性的致命弱点。根据这一想法，他与蔡树棠先生在1956年从粘性流体的纳维-斯托克斯方程出发，找到了均匀各向同性湍流在衰变后期的轴对称涡旋解。此后周先生又与是勋刚、李松年、黄永念、魏中磊、钮珍南等同志合作引进并验证了准相似条件，发展了均匀各向同性湍流理论，并于1982年获得国家自然科学二等奖。", "ei": "", "pc": "", "tm": "", "loc": "", "sm": ""}