{"person_Id": "0186", "source_text": "一个周末的下午，同学们都离开了实验室，只剩下钱三强一个人留在那里做分子光带分析。从南京开会回来的严老师进了实验室，看钱三强仍在聚经会神地工作，又看了看分析的数据结果，与国外的资料数据大致相同，心中无比高兴。他更加喜欢这位年轻人了，告诉钱三强，上半年将有中法教育文化基金会举行的留法考试，建议钱三强报考镭学名额。钱三强万万没有想到会有这个好机会，他从心里感激自己的老师。时间紧迫，10年没有读的法语，要尽快捡起。钱三强下定决心，要克服困难，认真地准备应考。考试完不久，严老师兴致勃勃地告诉他：“你考取了，考得不错。”钱三强收拾行李，就要离开生他养他的土地，就要离开重病在身的父亲，离开关心他抚育他的老师，他依依不舍。芦沟桥事变爆发，国难当头，又增加了他心头的沉重。他犹豫不决，不忍离开自己的故土。父亲忍着离别的痛苦劝导他，这是一次难得的学习机会，你学的东西会对祖国有用。报效祖国，造福社会，路程远得很哩！男儿立志，不能只顾近忧啊！1937年8月的一天，一艘远洋客轮载着钱三强，离开了上海港，驶向了波涛汹涌的大海。", "ei": "", "pc": "", "tm": "", "loc": "", "sm": ""}